colpali_engine/__init__.py
colpali_engine/collators/__init__.py
colpali_engine/collators/visual_retriever_collator.py
colpali_engine/compression/__init__.py
colpali_engine/compression/token_pooling/__init__.py
colpali_engine/compression/token_pooling/base_token_pooling.py
colpali_engine/compression/token_pooling/hierarchical_token_pooling.py
colpali_engine/compression/token_pooling/lambda_token_pooling.py
colpali_engine/data/__init__.py
colpali_engine/data/dataset.py
colpali_engine/data/sampler.py
colpali_engine/interpretability/__init__.py
colpali_engine/interpretability/similarity_map_utils.py
colpali_engine/interpretability/similarity_maps.py
colpali_engine/loss/__init__.py
colpali_engine/loss/bi_encoder_losses.py
colpali_engine/loss/late_interaction_losses.py
colpali_engine/models/__init__.py
colpali_engine/models/idefics3/__init__.py
colpali_engine/models/idefics3/biidefics3/__init__.py
colpali_engine/models/idefics3/biidefics3/modeling_biidefics3.py
colpali_engine/models/idefics3/biidefics3/processing_biidefics3.py
colpali_engine/models/idefics3/colidefics3/__init__.py
colpali_engine/models/idefics3/colidefics3/modeling_colidefics3.py
colpali_engine/models/idefics3/colidefics3/processing_colidefics3.py
colpali_engine/models/modernvbert/__init__.py
colpali_engine/models/modernvbert/configuration_modernvbert.py
colpali_engine/models/modernvbert/modeling_modernvbert.py
colpali_engine/models/modernvbert/bivbert/__init__.py
colpali_engine/models/modernvbert/bivbert/modeling_bimodernvbert.py
colpali_engine/models/modernvbert/bivbert/processing_bimodernvbert.py
colpali_engine/models/modernvbert/colvbert/__init__.py
colpali_engine/models/modernvbert/colvbert/modeling_colmodernvbert.py
colpali_engine/models/modernvbert/colvbert/processing_colmodernvbert.py
colpali_engine/models/paligemma/__init__.py
colpali_engine/models/paligemma/bipali/__init__.py
colpali_engine/models/paligemma/bipali/modeling_bipali.py
colpali_engine/models/paligemma/bipali/processing_bipali.py
colpali_engine-0.3.13.dist-info/METADATA
colpali_engine-0.3.13.dist-info/WHEEL
colpali_engine-0.3.13.dist-info/licenses/LICENSE
colpali_engine-0.3.13.dist-info/RECORD
