Metadata-Version: 2.4
Name: colpali_engine
Version: 0.3.13
Summary: The code used to train and run inference with the ColPali architecture.
Project-URL: homepage, https://github.com/illuin-tech/colpali
Author-email: Manuel Faysse <manuel.faysse@illuin.tech>, Hugues Sibille <hugues.sibille@illuin.tech>, Tony Wu <tony.wu@illuin.tech>
Maintainer-email: Manuel Faysse <manuel.faysse@illuin.tech>, Tony Wu <tony.wu@illuin.tech>
License-File: LICENSE
Classifier: Intended Audience :: Developers
Classifier: Intended Audience :: Science/Research
Classifier: License :: OSI Approved :: MIT License
Classifier: Operating System :: OS Independent
Classifier: Programming Language :: Python :: 3
Classifier: Topic :: Scientific/Engineering :: Artificial Intelligence
Requires-Python: >=3.9
Requires-Dist: numpy
Requires-Dist: peft<0.18.0,>=0.14.0
Requires-Dist: pillow>=10.0.0
Requires-Dist: requests
Requires-Dist: scipy
Requires-Dist: torch<2.9.0,>=2.2.0
Requires-Dist: torchvision
Requires-Dist: transformers<4.58.0,>=4.53.1
Provides-Extra: all
Requires-Dist: accelerate<1.9.0,>=0.34.0; extra == 'all'
Requires-Dist: bitsandbytes; extra == 'all'
Requires-Dist: configue>=5.0.0; extra == 'all'
Requires-Dist: datasets>=2.19.1; extra == 'all'
Requires-Dist: einops<1.0.0,>=0.8.0; extra == 'all'
Requires-Dist: matplotlib<4.0.0,>=3.9.0; extra == 'all'
Requires-Dist: mteb<2,>=1.16.3; extra == 'all'
Requires-Dist: pillow<11.4.0,>=10.0.0; extra == 'all'
Requires-Dist: pytest>=8.0.0; extra == 'all'
Requires-Dist: ruff>=0.4.0; extra == 'all'
Requires-Dist: seaborn<1.0.0,>=0.13.2; extra == 'all'
Requires-Dist: typer>=0.15.1; extra == 'all'
Provides-Extra: dev
Requires-Dist: pytest>=8.0.0; extra == 'dev'
Requires-Dist: ruff>=0.4.0; extra == 'dev'
Provides-Extra: interpretability
Requires-Dist: einops<1.0.0,>=0.8.0; extra == 'interpretability'
Requires-Dist: matplotlib<4.0.0,>=3.9.0; extra == 'interpretability'
Requires-Dist: seaborn<1.0.0,>=0.13.2; extra == 'interpretability'
Provides-Extra: train
Requires-Dist: accelerate<1.9.0,>=0.34.0; extra == 'train'
Requires-Dist: bitsandbytes; extra == 'train'
Requires-Dist: configue>=5.0.0; extra == 'train'
Requires-Dist: datasets>=2.19.1; extra == 'train'
Requires-Dist: mteb<2,>=1.16.3; extra == 'train'
Requires-Dist: pillow<11.4.0,>=10.0.0; extra == 'train'
Requires-Dist: typer>=0.15.1; extra == 'train'
